sentence_transformers/LoggingHandler.py
sentence_transformers/SentenceTransformer.py
sentence_transformers/SentenceTransformer.pyi
sentence_transformers/__init__.py
sentence_transformers/backend.py
sentence_transformers/data_collator.py
sentence_transformers/fit_mixin.py
sentence_transformers/model_card.py
sentence_transformers/model_card_template.md
sentence_transformers/model_card_templates.py
sentence_transformers/peft_mixin.py
sentence_transformers/py.typed
sentence_transformers/quantization.py
sentence_transformers/sampler.py
sentence_transformers/similarity_functions.py
sentence_transformers/trainer.py
sentence_transformers/training_args.py
sentence_transformers/util.py
sentence_transformers/cross_encoder/CrossEncoder.py
sentence_transformers/cross_encoder/__init__.py
sentence_transformers/cross_encoder/data_collator.py
sentence_transformers/cross_encoder/fit_mixin.py
sentence_transformers/cross_encoder/model_card.py
sentence_transformers/cross_encoder/trainer.py
sentence_transformers/cross_encoder/training_args.py
sentence_transformers/cross_encoder/util.py
sentence_transformers/cross_encoder/evaluation/__init__.py
sentence_transformers/cross_encoder/evaluation/classification.py
sentence_transformers/cross_encoder/evaluation/correlation.py
sentence_transformers/cross_encoder/evaluation/deprecated.py
sentence_transformers/cross_encoder/evaluation/nano_beir.py
sentence_transformers/cross_encoder/evaluation/reranking.py
sentence_transformers/cross_encoder/losses/BinaryCrossEntropyLoss.py
sentence_transformers/cross_encoder/losses/CachedMultipleNegativesRankingLoss.py
sentence_transformers/cross_encoder/losses/CrossEntropyLoss.py
sentence_transformers/cross_encoder/losses/LambdaLoss.py
sentence_transformers/cross_encoder/losses/ListMLELoss.py
sentence_transformers/cross_encoder/losses/ListNetLoss.py
sentence_transformers/cross_encoder/losses/MSELoss.py
sentence_transformers/cross_encoder/losses/MarginMSELoss.py
sentence_transformers-4.0.0.dist-info/licenses/LICENSE
sentence_transformers-4.0.0.dist-info/licenses/NOTICE.txt
sentence_transformers-4.0.0.dist-info/METADATA
sentence_transformers-4.0.0.dist-info/WHEEL
sentence_transformers-4.0.0.dist-info/top_level.txt
sentence_transformers-4.0.0.dist-info/RECORD
