Metadata-Version: 2.4
Name: sentence-transformers
Version: 4.0.0
Summary: Embeddings, Retrieval, and Reranking
Author-email: Nils Reimers <info@nils-reimers.de>, Tom Aarsen <tom.aarsen@huggingface.co>
Maintainer-email: Tom Aarsen <tom.aarsen@huggingface.co>
License: Apache 2.0
Project-URL: Homepage, https://www.SBERT.net
Project-URL: Repository, https://github.com/UKPLab/sentence-transformers/
Keywords: Transformer Networks,BERT,XLNet,sentence embedding,PyTorch,NLP,deep learning
Classifier: Development Status :: 5 - Production/Stable
Classifier: Intended Audience :: Science/Research
Classifier: License :: OSI Approved :: Apache Software License
Classifier: Programming Language :: Python :: 3.9
Classifier: Programming Language :: Python :: 3.10
Classifier: Programming Language :: Python :: 3.11
Classifier: Programming Language :: Python :: 3.12
Classifier: Topic :: Scientific/Engineering :: Artificial Intelligence
Requires-Python: >=3.9
License-File: LICENSE
License-File: NOTICE.txt
Requires-Dist: transformers<5.0.0,>=4.41.0
Requires-Dist: tqdm
Requires-Dist: torch>=1.11.0
Requires-Dist: scikit-learn
Requires-Dist: scipy
Requires-Dist: huggingface-hub>=0.20.0
Requires-Dist: Pillow
Requires-Dist: typing_extensions>=4.5.0
Provides-Extra: train
Requires-Dist: datasets; extra == "train"
Requires-Dist: accelerate>=0.20.3; extra == "train"
Provides-Extra: onnx
Requires-Dist: optimum[onnxruntime]>=1.23.1; extra == "onnx"
Provides-Extra: onnx-gpu
Requires-Dist: optimum[onnxruntime-gpu]>=1.23.1; extra == "onnx-gpu"
Provides-Extra: openvino
Requires-Dist: optimum-intel[openvino]>=1.20.0; extra == "openvino"
Provides-Extra: dev
Requires-Dist: datasets; extra == "dev"
Requires-Dist: accelerate>=0.20.3; extra == "dev"
Requires-Dist: pre-commit; extra == "dev"
Requires-Dist: pytest; extra == "dev"
Requires-Dist: pytest-cov; extra == "dev"
Requires-Dist: peft; extra == "dev"
Dynamic: license-file
